PyL2BV/__init__.py
PyL2BV/cli.py
PyL2BV/gui.py
PyL2BV/pyl2bv_code/__init__.py
PyL2BV/pyl2bv_code/auxiliar/__init__.py
PyL2BV/pyl2bv_code/auxiliar/image_read.py
PyL2BV/pyl2bv_code/auxiliar/logger_config.py
PyL2BV/pyl2bv_code/auxiliar/spectra_interpolation.py
PyL2BV/pyl2bv_code/model_runner.py
PyL2BV/pyl2bv_code/processing/__init__.py
PyL2BV/pyl2bv_code/processing/mlra.py
PyL2BV/pyl2bv_code/processing/mlra_gpr.py
PyL2BV/pyl2bv_code/processing/processing_module.py
PyL2BV/pyl2bv_code/processing/retrieval.py
pyl2bv-1.1.6.dist-info/entry_points.txt
pyl2bv-1.1.6.dist-info/LICENSE
pyl2bv-1.1.6.dist-info/METADATA
pyl2bv-1.1.6.dist-info/WHEEL
pyl2bv-1.1.6.dist-info/RECORD
