Metadata-Version: 2.3
Name: pyl2bv
Version: 1.1.6
Summary: Package for vegetation trait retrievals with ARTMO-based GPR models from hyperspectral images.
Keywords: vegetation,retrieval,ARTMO,GPR,hyperspectral
Author: Viktor Ixion Mészáros
Author-email: viktor.meszaros@uv.es
Requires-Python: >=3.10
Classifier: Programming Language :: Python :: 3
Classifier: License :: OSI Approved :: Apache Software License
Classifier: Operating System :: OS Independent
Requires-Dist: joblib (>=1.4.0,<2.0.0)
Requires-Dist: matplotlib (>=3.9.0,<4.0.0)
Requires-Dist: netCDF4 (>=1.7.0,<2.0.0)
Requires-Dist: numpy (>=2.0.0,<3.0.0)
Requires-Dist: pyproj (>=3.7.0,<4.0.0)
Requires-Dist: scipy (>=1.14.0,<2.0.0)
Requires-Dist: spectral (>=0.23.0,<0.24.0)
Project-URL: Homepage, https://github.com/mv-xion/PyL2BV
Project-URL: Issues, https://github.com/mv-xion/PyL2BV/issues
